<?xml version="1.0" encoding="UTF-8"?>
<Invoice xmlns:cbc="urn:oasis:names:specification:ubl:schema:xsd:CommonBasicComponents-2" xmlns:udt="urn:oasis:names:specification:ubl:schema:xsd:UnqualifiedDataTypes-2" xmlns:cac="urn:oasis:names:specification:ubl:schema:xsd:CommonAggregateComponents-2" xmlns:ccts="urn:un:unece:uncefact:documentation:2" xmlns="urn:oasis:names:specification:ubl:schema:xsd:Invoice-2" xmlns:qdt="urn:oasis:names:specification:ubl:schema:xsd:QualifiedDataTypes-2" xmlns:xsi="http://www.w3.org/2001/XMLSchema-instance"><cbc:UBLVersionID>2.1</cbc:UBLVersionID><cbc:CustomizationID>urn:cen.eu:en16931:2017#compliant#urn:efactura.mfinante.ro:CIUS-RO:1.0.1</cbc:CustomizationID><cbc:ID>CONAF 081</cbc:ID><cbc:IssueDate>2024-02-26</cbc:IssueDate><cbc:DueDate>2024-02-26</cbc:DueDate><cbc:InvoiceTypeCode>380</cbc:InvoiceTypeCode><cbc:Note>Valabil fara semnatura si stampila cf. Art. 319 (29) din Codul Fiscal.</cbc:Note><cbc:Note>Factura se achita cu ordin de plata in contul RO43UGBI0000122021481RON deschis la GARANTIBANK</cbc:Note><cbc:DocumentCurrencyCode>RON</cbc:DocumentCurrencyCode><cbc:TaxCurrencyCode>RON</cbc:TaxCurrencyCode><cac:AccountingSupplierParty><cac:Party><cac:PartyIdentification><cbc:ID>40510491</cbc:ID></cac:PartyIdentification><cac:PostalAddress><cbc:StreetName>str. CUZA VODA nr. 120 et. 1 ap. 2</cbc:StreetName><cbc:CityName>SECTOR4</cbc:CityName><cbc:CountrySubentity>RO-B</cbc:CountrySubentity><cac:Country><cbc:IdentificationCode>RO</cbc:IdentificationCode></cac:Country></cac:PostalAddress><cac:PartyTaxScheme><cbc:CompanyID>40510491</cbc:CompanyID><cac:TaxScheme/></cac:PartyTaxScheme><cac:PartyLegalEntity><cbc:RegistrationName>CONFEDERATIA NATIONALA PENTRU ANTREPRENORIAT FEMININ - CONAF</cbc:RegistrationName><cbc:CompanyID>29255/3/2018</cbc:CompanyID></cac:PartyLegalEntity><cac:Contact><cbc:Name>IONITA GIANINA</cbc:Name><cbc:Telephone>0724577077</cbc:Telephone><cbc:ElectronicMail>office@conaf.ro</cbc:ElectronicMail></cac:Contact></cac:Party></cac:AccountingSupplierParty><cac:AccountingCustomerParty><cac:Party><cac:PartyIdentification><cbc:ID>RO4879159</cbc:ID></cac:PartyIdentification><cac:PostalAddress><cbc:StreetName>SOS. FABRICA DE GLUCOZA, NR. 17</cbc:StreetName><cbc:CityName>SECTOR2</cbc:CityName><cbc:CountrySubentity>RO-B</cbc:CountrySubentity><cac:Country><cbc:IdentificationCode>RO</cbc:IdentificationCode></cac:Country></cac:PostalAddress><cac:PartyTaxScheme><cbc:CompanyID>RO4879159</cbc:CompanyID><cac:TaxScheme/></cac:PartyTaxScheme><cac:PartyLegalEntity><cbc:RegistrationName>INTRAROM S.A.</cbc:RegistrationName><cbc:CompanyID>RO4879159</cbc:CompanyID></cac:PartyLegalEntity></cac:Party></cac:AccountingCustomerParty><cac:PaymentMeans><cbc:PaymentMeansCode>42</cbc:PaymentMeansCode><cac:PayeeFinancialAccount><cbc:ID>RO43UGBI0000122021481RON</cbc:ID><cbc:Name>GARANTIBANK</cbc:Name></cac:PayeeFinancialAccount></cac:PaymentMeans><cac:TaxTotal><cbc:TaxAmount currencyID="RON">0.00</cbc:TaxAmount><cac:TaxSubtotal><cbc:TaxableAmount currencyID="RON">400.00</cbc:TaxableAmount><cbc:TaxAmount currencyID="RON">0.00</cbc:TaxAmount><cac:TaxCategory><cbc:ID>O</cbc:ID><cbc:TaxExemptionReasonCode>VATEX-EU-O</cbc:TaxExemptionReasonCode><cbc:TaxExemptionReason>Entitatea nu este inregistrata in scopuri de TVA</cbc:TaxExemptionReason><cac:TaxScheme><cbc:ID>VAT</cbc:ID></cac:TaxScheme></cac:TaxCategory></cac:TaxSubtotal></cac:TaxTotal><cac:LegalMonetaryTotal><cbc:LineExtensionAmount currencyID="RON">400.00</cbc:LineExtensionAmount><cbc:TaxExclusiveAmount currencyID="RON">400.00</cbc:TaxExclusiveAmount><cbc:TaxInclusiveAmount currencyID="RON">400.00</cbc:TaxInclusiveAmount><cbc:PayableAmount currencyID="RON">400.00</cbc:PayableAmount></cac:LegalMonetaryTotal><cac:InvoiceLine><cbc:ID>1</cbc:ID><cbc:InvoicedQuantity unitCode="H87">2.000</cbc:InvoicedQuantity><cbc:LineExtensionAmount currencyID="RON">400.00</cbc:LineExtensionAmount><cac:Item><cbc:Name>TAXA DE PARTICIPARE</cbc:Name><cac:ClassifiedTaxCategory><cbc:ID>O</cbc:ID><cac:TaxScheme><cbc:ID>VAT</cbc:ID></cac:TaxScheme></cac:ClassifiedTaxCategory></cac:Item><cac:Price><cbc:PriceAmount currencyID="RON">200.0000</cbc:PriceAmount></cac:Price></cac:InvoiceLine></Invoice>
